greymatter/__init__.py
greymatter/chrome.py
greymatter/enums.py
greymatter/exceptions.py
greymatter-0.1a1.dist-info/LICENSE
greymatter-0.1a1.dist-info/METADATA
greymatter-0.1a1.dist-info/WHEEL
greymatter-0.1a1.dist-info/top_level.txt
greymatter-0.1a1.dist-info/RECORD
